MANIFEST.in
README.md
setup.py
gbif/__init__.py
gbif/models.py
gbif.egg-info/PKG-INFO
gbif.egg-info/SOURCES.txt
gbif.egg-info/dependency_links.txt
gbif.egg-info/requires.txt
gbif.egg-info/top_level.txt
gbif.egg-info/zip-safe