Metadata-Version: 1.0
Name: gbif
Version: 0.1.0
Summary: Basic and experimental Gbif Taxon API library for Python
Home-page: http://github.com/matagus/python-gbif
Author: Matías Agustín Méndez
Author-email: matagus@gmail.com
License: MIT
Keywords: gbif taxon taxonomy api bio
Platform: any
Classifier: Development Status :: 4 - Beta
Classifier: Intended Audience :: Developers
Classifier: License :: OSI Approved :: MIT License
Classifier: Operating System :: OS Independent
Classifier: Programming Language :: Python
Classifier: Programming Language :: Python :: 2
Classifier: Programming Language :: Python :: 2.4
Classifier: Programming Language :: Python :: 2.5
Classifier: Programming Language :: Python :: 2.6
Classifier: Programming Language :: Python :: 2.7
Classifier: Programming Language :: Python :: 3
Classifier: Programming Language :: Python :: 3.1
Classifier: Programming Language :: Python :: 3.2
Classifier: Topic :: Software Development
Classifier: Topic :: Software Development :: Libraries
